{
    "duration": 0.34831249713897705,
    "lossless": 1.0,
    "codec": "pcm_s16le",
    "bitrate": 256000.0,
    "samplerate": 16000.0,
    "channels": 1.0,
    "audio_md5": "c4479a68776294fdf261f8b05b5bf4c9",
    "loudness": -28.32151985168457,
    "dynamic_range": 0.0,
    "temporal_centroid": 0.1852279007434845,
    "log_attack_time": -1.77053701877594,
    "filesize": 11190,
    "single_event": true,
    "hardness": 67.49244203710859,
    "depth": 3.8386471360443437,
    "brightness": 83.79986432041585,
    "roughness": 64.50813430319835,
    "warmth": 17.439775584723815,
    "sharpness": 88.02515670427255,
    "boominess": 3.6009335836593763,
    "reverb": false
}