{
    "duration": 0.2591874897480011,
    "lossless": 1.0,
    "codec": "pcm_s16le",
    "bitrate": 256000.0,
    "samplerate": 16000.0,
    "channels": 1.0,
    "audio_md5": "4dff855d6c4642467e9652b5f50caf66",
    "loudness": -19.22913932800293,
    "dynamic_range": 0.0,
    "temporal_centroid": 0.3726336359977722,
    "log_attack_time": -1.2895622253417969,
    "filesize": 8338,
    "single_event": true,
    "hardness": 65.61483999653001,
    "depth": 23.378150857350853,
    "brightness": 80.8476568699698,
    "roughness": 74.15832194027234,
    "warmth": 17.748538542648312,
    "sharpness": 75.61723624003827,
    "boominess": 0.0,
    "reverb": false
}