{
    "duration": 0.09274999797344208,
    "lossless": 1.0,
    "codec": "pcm_s16le",
    "bitrate": 256000.0,
    "samplerate": 16000.0,
    "channels": 1.0,
    "audio_md5": "5430444b9415cd64c8a782feccc92b61",
    "loudness": -30.891138076782227,
    "dynamic_range": 0.0,
    "temporal_centroid": 0.5036866068840027,
    "log_attack_time": -2.5545334815979004,
    "filesize": 3012,
    "single_event": true,
    "hardness": 74.45054470675782,
    "depth": 15.589681544878161,
    "brightness": 79.7215006366634,
    "roughness": 67.87563399249443,
    "warmth": 29.97007973387347,
    "sharpness": 76.31260828199395,
    "boominess": 3.724389950844351,
    "reverb": false
}