{
    "duration": 0.021124999970197678,
    "lossless": 1.0,
    "codec": "pcm_s16le",
    "bitrate": 256000.0,
    "samplerate": 16000.0,
    "channels": 1.0,
    "audio_md5": "9a985692eb8bb4dd0d7d0d9cb150658a",
    "loudness": -26.875652313232422,
    "dynamic_range": 0.0,
    "temporal_centroid": 0.5575769543647766,
    "log_attack_time": -2.3796207904815674,
    "filesize": 720,
    "single_event": true,
    "hardness": 75.55065670024783,
    "depth": 13.190274114851768,
    "brightness": 70.40787303422775,
    "roughness": 56.0065218579545,
    "warmth": 28.306082873434228,
    "sharpness": 63.88356120747827,
    "boominess": 0.0,
    "reverb": false
}