{
    "duration": 0.3018749952316284,
    "lossless": 1.0,
    "codec": "pcm_s16le",
    "bitrate": 256000.0,
    "samplerate": 16000.0,
    "channels": 1.0,
    "audio_md5": "0adf152e6fed62f53c7b259c4bc644c2",
    "loudness": -23.18523597717285,
    "dynamic_range": 0.0,
    "temporal_centroid": 0.2001291811466217,
    "log_attack_time": -1.7811157703399658,
    "filesize": 9704,
    "single_event": true,
    "hardness": 70.70236120056217,
    "depth": 46.718316928533454,
    "brightness": 67.8699672578198,
    "roughness": 64.08832495294561,
    "warmth": 31.735370640539642,
    "sharpness": 60.930130257188,
    "boominess": 28.24281830581663,
    "reverb": false
}