{
    "duration": 0.48762500286102295,
    "lossless": 1.0,
    "codec": "pcm_s16le",
    "bitrate": 256000.0,
    "samplerate": 16000.0,
    "channels": 1.0,
    "audio_md5": "9327c4d4ae7508104d1c54c86351ae1d",
    "loudness": -22.929500579833984,
    "dynamic_range": 0.0,
    "temporal_centroid": 0.14736594259738922,
    "log_attack_time": -1.9569096565246582,
    "filesize": 15648,
    "single_event": true,
    "hardness": 71.42833597749231,
    "depth": 32.527443398863355,
    "brightness": 73.9774668006471,
    "roughness": 63.220553580977764,
    "warmth": 25.890030699667694,
    "sharpness": 63.72443932291733,
    "boominess": 18.024672296535925,
    "reverb": false
}