{
    "duration": 0.34831249713897705,
    "lossless": 1.0,
    "codec": "pcm_s16le",
    "bitrate": 256000.0,
    "samplerate": 16000.0,
    "channels": 1.0,
    "audio_md5": "d24916641d96fdd894d3c57fd728c8a1",
    "loudness": -18.792081832885742,
    "dynamic_range": 0.0,
    "temporal_centroid": 0.2135971635580063,
    "log_attack_time": -1.5609359741210938,
    "filesize": 11190,
    "single_event": true,
    "hardness": 34.55663219370331,
    "depth": 69.6724790997584,
    "brightness": 26.05381618798649,
    "roughness": 32.66705881478466,
    "warmth": 57.175523084553916,
    "sharpness": 6.49491350500438,
    "boominess": 58.075164613665905,
    "reverb": false
}