{
    "duration": 0.20900000631809235,
    "lossless": 1.0,
    "codec": "pcm_s16le",
    "bitrate": 256000.0,
    "samplerate": 16000.0,
    "channels": 1.0,
    "audio_md5": "1f27848c0c2f7fce324265f78b8af8ff",
    "loudness": -33.11878967285156,
    "dynamic_range": 0.0,
    "temporal_centroid": 0.2707200348377228,
    "log_attack_time": -2.195732355117798,
    "filesize": 6732,
    "single_event": true,
    "hardness": 75.98086658857835,
    "depth": 24.017915681880922,
    "brightness": 75.32327543976368,
    "roughness": 64.50501586953527,
    "warmth": 27.819633388038106,
    "sharpness": 76.47302536390517,
    "boominess": 0.0,
    "reverb": false
}