{
    "duration": 0.48762500286102295,
    "lossless": 1.0,
    "codec": "pcm_s16le",
    "bitrate": 256000.0,
    "samplerate": 16000.0,
    "channels": 1.0,
    "audio_md5": "930e4fb1eee8bbfb3dadb8affcdf98a6",
    "loudness": -30.628238677978516,
    "dynamic_range": 0.0,
    "temporal_centroid": 0.2519546449184418,
    "log_attack_time": -1.9668315649032593,
    "filesize": 15648,
    "single_event": true,
    "hardness": 62.10917613032677,
    "depth": 14.537221514093595,
    "brightness": 79.06090758900109,
    "roughness": 56.16234439084291,
    "warmth": 14.911626699204533,
    "sharpness": 74.62669637242817,
    "boominess": 0.0,
    "reverb": false
}