{
    "duration": 0.3947499990463257,
    "lossless": 1.0,
    "codec": "pcm_s16le",
    "bitrate": 256000.0,
    "samplerate": 16000.0,
    "channels": 1.0,
    "audio_md5": "e34ce7a64ca39f67be300c9edf85fdbe",
    "loudness": -23.052993774414062,
    "dynamic_range": 0.0,
    "temporal_centroid": 0.2407018393278122,
    "log_attack_time": -2.119393825531006,
    "filesize": 12676,
    "single_event": true,
    "hardness": 70.4846963479315,
    "depth": 34.44054519277382,
    "brightness": 74.82246358039733,
    "roughness": 69.939800323545,
    "warmth": 30.10713521488355,
    "sharpness": 66.02073167130769,
    "boominess": 18.976281025446,
    "reverb": false
}