{
    "duration": 0.6858749985694885,
    "lossless": 1.0,
    "codec": "pcm_s16le",
    "bitrate": 256000.0,
    "samplerate": 16000.0,
    "channels": 1.0,
    "audio_md5": "e8f8607256be0f7f157dfce377a0a73e",
    "loudness": -22.272422790527344,
    "dynamic_range": 0.0,
    "temporal_centroid": 0.16350629925727844,
    "log_attack_time": -1.7699568271636963,
    "filesize": 21992,
    "single_event": true,
    "hardness": 69.13643301962742,
    "depth": 32.932596994153236,
    "brightness": 82.71903401552711,
    "roughness": 61.755675744542536,
    "warmth": 16.10821301122925,
    "sharpness": 80.4449969087961,
    "boominess": 6.713370662643534,
    "reverb": false
}