{
    "duration": 0.5805000066757202,
    "lossless": 1.0,
    "codec": "pcm_s16le",
    "bitrate": 256000.0,
    "samplerate": 16000.0,
    "channels": 1.0,
    "audio_md5": "d3b0a923f650a916fcba0b39119d124f",
    "loudness": -21.419170379638672,
    "dynamic_range": 0.0,
    "temporal_centroid": 0.14738023281097412,
    "log_attack_time": -1.7619140148162842,
    "filesize": 18620,
    "single_event": true,
    "hardness": 58.94482478467171,
    "depth": 61.028414818128226,
    "brightness": 42.47878087942788,
    "roughness": 40.13216251638414,
    "warmth": 56.136964011578556,
    "sharpness": 36.66694209526599,
    "boominess": 40.921714176556975,
    "reverb": false
}