{
    "duration": 0.4411875009536743,
    "lossless": 1.0,
    "codec": "pcm_s16le",
    "bitrate": 256000.0,
    "samplerate": 16000.0,
    "channels": 1.0,
    "audio_md5": "2a82770b5a288317781372f1b7df2afe",
    "loudness": -15.879947662353516,
    "dynamic_range": 0.0,
    "temporal_centroid": 0.3399297893047333,
    "log_attack_time": -1.1607086658477783,
    "filesize": 14162,
    "single_event": true,
    "hardness": 48.70082029972846,
    "depth": 70.57194322451183,
    "brightness": 44.736440476725,
    "roughness": 44.15560687803007,
    "warmth": 57.74729821202523,
    "sharpness": 44.915959059358585,
    "boominess": 44.94637408560044,
    "reverb": false
}