{
    "duration": 0.31975001096725464,
    "lossless": 1.0,
    "codec": "pcm_s16le",
    "bitrate": 256000.0,
    "samplerate": 16000.0,
    "channels": 1.0,
    "audio_md5": "3503f02c4e1ec64eba7fff845702ec5d",
    "loudness": -19.552501678466797,
    "dynamic_range": 0.0,
    "temporal_centroid": 0.2488740235567093,
    "log_attack_time": -1.8923901319503784,
    "filesize": 10276,
    "single_event": true,
    "hardness": 41.34952774943352,
    "depth": 65.11709665186935,
    "brightness": 41.88003755151686,
    "roughness": 41.14339938732721,
    "warmth": 56.913742869958895,
    "sharpness": 31.34211895590474,
    "boominess": 48.316952716851574,
    "reverb": false
}