{
    "duration": 0.1625625044107437,
    "lossless": 1.0,
    "codec": "pcm_s16le",
    "bitrate": 256000.0,
    "samplerate": 16000.0,
    "channels": 1.0,
    "audio_md5": "c0bfd524abbdd3824150537dcd6679b6",
    "loudness": -23.217100143432617,
    "dynamic_range": 0.0,
    "temporal_centroid": 0.3513610064983368,
    "log_attack_time": -1.6603615283966064,
    "filesize": 5246,
    "single_event": true,
    "hardness": 72.94707984532886,
    "depth": 17.398673111181658,
    "brightness": 81.92409405923479,
    "roughness": 71.90060588668972,
    "warmth": 13.196586517184826,
    "sharpness": 77.35148812448963,
    "boominess": 0.0,
    "reverb": false
}